{"name":"cmd_line","tagline":"Provides easy-to-use functions for handling arguments input from shell (C++)","body":"# cmd_line\r\nThe library wraps simple functios that handles input for shell for C++ projects.\r\n# Exmaple\r\nWe define an argument like this:\r\n```\r\n  cmdline.add(\"-i\", \"your integer\", &i, 73);\r\n```\r\n\r\nFirst, we indicated the tag that precedes our arguemnt (`-i`), then we added a description (`\"your integer\"`), and finally we used a default value of `73`.\r\nWe then have to call the parse command which handles the input:\r\n```\r\n   int rc = cmdline.parse(argc, argv);\r\n```\r\nIn this example, `rc` will hold the number of arguments given.\r\nWe can check what arguments we recieved:\r\n```\r\n  if (rc < 1) {\r\n    cmdline.print_help();\r\n    return EXIT_FAILURE;\r\n  }\r\n```\r\n  \r\nThen, the value entered by the user will then be stored in `i`\r\n```\r\n   std::cout << \"i=\" << i << std::endl;\r\n```","google":"","note":"Don't delete this file! It's used internally to help with page regeneration."}